MedicalImageConversion/__init__.py
MedicalImageConversion/main.py
MedicalImageConversion/nii2dcm.py
MedicalImageConversion-1.1.0.0.dist-info/LICENSE
MedicalImageConversion-1.1.0.0.dist-info/METADATA
MedicalImageConversion-1.1.0.0.dist-info/WHEEL
MedicalImageConversion-1.1.0.0.dist-info/top_level.txt
MedicalImageConversion-1.1.0.0.dist-info/RECORD
