Metadata-Version: 2.1
Name: MedicalImageConversion
Version: 1.1.0.0
Summary: Medical image conversion
Author-email: tekhinvasiliy@gmail.com
License-File: LICENSE
